PrintVerbose/__init__.py
PrintVerbose/logger.py
printverbose-1.1.1.dist-info/licenses/LICENSE
printverbose-1.1.1.dist-info/METADATA
printverbose-1.1.1.dist-info/WHEEL
printverbose-1.1.1.dist-info/top_level.txt
printverbose-1.1.1.dist-info/RECORD
