Metadata-Version: 2.4
Name: PrintVerbose
Version: 1.1.1
Summary: Colorized logging with traceback dumping
Author: Quad
Requires-Python: >=3.8
License-File: LICENSE
Requires-Dist: colorama
Dynamic: license-file
